{
  "crimeVersion": {
    "crimeVersionId": "252a9a57-337f-4208-908b-2874b75fa10f",
    "crimeReference": "CR-2026-000123",
    "crimeType": "Burglary",
    "fromDateTime": "2026-01-16T08:00:00Z",
    "toDateTime": "2026-01-16T09:00:00Z",
    "latitude": 51.5745,
    "longitude": 0.060299,
    "crimeText": "Suspect seen near address shortly after break-in."
  },
  "matchedDeviceWearers": [
    {
      "deviceWearerId": "604008982",
      "name": "Richard Gibbons",
      "nomisId": "A5128CZ",
      "deviceId": 604008982,
      "positions": [
        {
          "positionId": "A1",
          "capturedDateTime": "2026-01-16T08:12:03Z",
          "sequenceLabel": "A1",
          "latitude": 51.57414,
          "longitude": 0.06001,
          "confidenceCircle": 10
        },
        {
          "positionId": "A2",
          "capturedDateTime": "2026-01-16T08:15:03Z",
          "sequenceLabel": "A2",
          "latitude": 51.57416,
          "longitude": 0.06003,
          "confidenceCircle": 8
        },
        {
          "positionId": "A3",
          "capturedDateTime": "2026-01-16T08:18:03Z",
          "sequenceLabel": "A3",
          "latitude": 51.57412,
          "longitude": 0.05999,
          "confidenceCircle": 13
        }
      ]
    }
  ]
}
